{
  "registros": {
    "2026-05-17": [
      {
        "hora": "11:21:36",
        "con_cupos": 10,
        "total_cupos": 168,
        "cambios": 1
      },
      {
        "hora": "11:22:04",
        "con_cupos": 10,
        "total_cupos": 168,
        "cambios": 0
      },
      {
        "hora": "11:27:05",
        "con_cupos": 10,
        "total_cupos": 168,
        "cambios": 0
      },
      {
        "hora": "11:32:06",
        "con_cupos": 10,
        "total_cupos": 168,
        "cambios": 0
      },
      {
        "hora": "11:37:07",
        "con_cupos": 10,
        "total_cupos": 168,
        "cambios": 0
      },
      {
        "hora": "11:42:09",
        "con_cupos": 10,
        "total_cupos": 168,
        "cambios": 0
      }
    ],
    "2026-05-21": [
      {
        "hora": "08:33:12",
        "con_cupos": 11,
        "total_cupos": 151,
        "cambios": 4
      },
      {
        "hora": "08:37:33",
        "con_cupos": 11,
        "total_cupos": 150,
        "cambios": 0
      },
      {
        "hora": "08:42:34",
        "con_cupos": 11,
        "total_cupos": 149,
        "cambios": 0
      },
      {
        "hora": "08:47:35",
        "con_cupos": 11,
        "total_cupos": 149,
        "cambios": 0
      },
      {
        "hora": "08:52:36",
        "con_cupos": 11,
        "total_cupos": 148,
        "cambios": 0
      },
      {
        "hora": "08:57:37",
        "con_cupos": 11,
        "total_cupos": 147,
        "cambios": 0
      },
      {
        "hora": "09:02:38",
        "con_cupos": 11,
        "total_cupos": 147,
        "cambios": 0
      },
      {
        "hora": "09:03:03",
        "con_cupos": 11,
        "total_cupos": 147,
        "cambios": 0
      },
      {
        "hora": "09:09:29",
        "con_cupos": 11,
        "total_cupos": 145,
        "cambios": 0
      },
      {
        "hora": "09:10:31",
        "con_cupos": 11,
        "total_cupos": 145,
        "cambios": 0
      },
      {
        "hora": "09:15:32",
        "con_cupos": 11,
        "total_cupos": 144,
        "cambios": 0
      },
      {
        "hora": "09:15:54",
        "con_cupos": 11,
        "total_cupos": 144,
        "cambios": 0
      },
      {
        "hora": "09:16:02",
        "con_cupos": 11,
        "total_cupos": 144,
        "cambios": 0
      },
      {
        "hora": "09:21:05",
        "con_cupos": 11,
        "total_cupos": 142,
        "cambios": 0
      },
      {
        "hora": "09:26:08",
        "con_cupos": 11,
        "total_cupos": 142,
        "cambios": 0
      },
      {
        "hora": "09:31:10",
        "con_cupos": 11,
        "total_cupos": 141,
        "cambios": 0
      },
      {
        "hora": "09:34:04",
        "con_cupos": 11,
        "total_cupos": 141,
        "cambios": 0
      },
      {
        "hora": "09:34:54",
        "con_cupos": 11,
        "total_cupos": 140,
        "cambios": 0
      },
      {
        "hora": "09:39:57",
        "con_cupos": 11,
        "total_cupos": 140,
        "cambios": 0
      },
      {
        "hora": "09:45:00",
        "con_cupos": 11,
        "total_cupos": 140,
        "cambios": 0
      },
      {
        "hora": "09:50:03",
        "con_cupos": 11,
        "total_cupos": 140,
        "cambios": 0
      },
      {
        "hora": "09:55:06",
        "con_cupos": 11,
        "total_cupos": 140,
        "cambios": 0
      },
      {
        "hora": "15:27:28",
        "con_cupos": 15,
        "total_cupos": 133,
        "cambios": 1
      },
      {
        "hora": "19:51:17",
        "con_cupos": 14,
        "total_cupos": 118,
        "cambios": 1
      }
    ],
    "2026-05-22": [
      {
        "hora": "06:41:13",
        "con_cupos": 12,
        "total_cupos": 100,
        "cambios": 1
      },
      {
        "hora": "07:31:57",
        "con_cupos": 12,
        "total_cupos": 100,
        "cambios": 1
      },
      {
        "hora": "07:34:45",
        "con_cupos": 12,
        "total_cupos": 100,
        "cambios": 0
      },
      {
        "hora": "07:51:39",
        "con_cupos": 12,
        "total_cupos": 100,
        "cambios": 1
      },
      {
        "hora": "07:53:49",
        "con_cupos": 12,
        "total_cupos": 100,
        "cambios": 1
      },
      {
        "hora": "07:58:44",
        "con_cupos": 12,
        "total_cupos": 100,
        "cambios": 1
      },
      {
        "hora": "08:51:27",
        "con_cupos": 11,
        "total_cupos": 96,
        "cambios": 2
      },
      {
        "hora": "09:18:28",
        "con_cupos": 11,
        "total_cupos": 94,
        "cambios": 0
      }
    ]
  },
  "eventos": [
    {
      "fecha": "2026-05-17T11:21:36.061539-03:00",
      "tipo": "nuevos",
      "especialidad": "PEDIATRIA CONSULTA",
      "cupos": 69
    },
    {
      "fecha": "2026-05-17T11:21:36.061539-03:00",
      "tipo": "nuevos",
      "especialidad": "CIRUGIA GENERAL",
      "cupos": 1
    },
    {
      "fecha": "2026-05-17T11:21:36.061539-03:00",
      "tipo": "nuevos",
      "especialidad": "CIRUGIA INFANTIL",
      "cupos": 1
    },
    {
      "fecha": "2026-05-17T11:21:36.061539-03:00",
      "tipo": "nuevos",
      "especialidad": "CLINICA MEDICA CONSULTA",
      "cupos": 45
    },
    {
      "fecha": "2026-05-17T11:21:36.061539-03:00",
      "tipo": "nuevos",
      "especialidad": "HEMATOLOGIA CLINICA",
      "cupos": 1
    },
    {
      "fecha": "2026-05-17T11:21:36.061539-03:00",
      "tipo": "nuevos",
      "especialidad": "INFECTOLOGIA PEDIATRICA",
      "cupos": 1
    },
    {
      "fecha": "2026-05-17T11:21:36.061539-03:00",
      "tipo": "nuevos",
      "especialidad": "PATOLOGIA MAMARIA (CON DERIVACION OBLIGATORIA)",
      "cupos": 1
    },
    {
      "fecha": "2026-05-17T11:21:36.061539-03:00",
      "tipo": "nuevos",
      "especialidad": "OBSTETRICIA BAJO RIESGO",
      "cupos": 17
    },
    {
      "fecha": "2026-05-17T11:21:36.061539-03:00",
      "tipo": "nuevos",
      "especialidad": "ONCOLOGIA",
      "cupos": 23
    },
    {
      "fecha": "2026-05-17T11:21:36.061539-03:00",
      "tipo": "nuevos",
      "especialidad": "CIRUGIA TORACICA",
      "cupos": 9
    },
    {
      "fecha": "2026-05-21T08:33:12.332314-03:00",
      "tipo": "nuevos",
      "especialidad": "CUIDADOS PALIATIVOS CON DERIVACION OBLIGATORIA",
      "cupos": 10
    },
    {
      "fecha": "2026-05-21T08:33:12.332314-03:00",
      "tipo": "nuevos",
      "especialidad": "INFECTOLOGIA",
      "cupos": 1
    },
    {
      "fecha": "2026-05-21T08:33:12.332314-03:00",
      "tipo": "nuevos",
      "especialidad": "PRE ANESTESIA PEDIATRIA",
      "cupos": 1
    },
    {
      "fecha": "2026-05-21T08:33:12.332314-03:00",
      "tipo": "nuevos",
      "especialidad": "COLOPROCTOLOGIA",
      "cupos": 2
    },
    {
      "fecha": "2026-05-21T08:33:12.332314-03:00",
      "tipo": "nuevos",
      "especialidad": "PODOLOGIA",
      "cupos": 13
    },
    {
      "fecha": "2026-05-21T08:33:12.332314-03:00",
      "tipo": "aumentos",
      "especialidad": "CIRUGIA GENERAL",
      "cupos": 33
    },
    {
      "fecha": "2026-05-21T08:33:12.332314-03:00",
      "tipo": "aumentos",
      "especialidad": "CIRUGIA INFANTIL",
      "cupos": 29
    },
    {
      "fecha": "2026-05-21T08:33:12.332314-03:00",
      "tipo": "aumentos",
      "especialidad": "OBSTETRICIA BAJO RIESGO",
      "cupos": 50
    },
    {
      "fecha": "2026-05-21T08:33:12.332314-03:00",
      "tipo": "ultimos",
      "especialidad": "ONCOLOGIA",
      "cupos": 3
    },
    {
      "fecha": "2026-05-21T08:33:12.332314-03:00",
      "tipo": "agotados",
      "especialidad": "PEDIATRIA CONSULTA",
      "cupos": 0
    },
    {
      "fecha": "2026-05-21T08:33:12.332314-03:00",
      "tipo": "agotados",
      "especialidad": "CLINICA MEDICA CONSULTA",
      "cupos": 0
    },
    {
      "fecha": "2026-05-21T08:33:12.332314-03:00",
      "tipo": "agotados",
      "especialidad": "HEMATOLOGIA CLINICA",
      "cupos": 0
    },
    {
      "fecha": "2026-05-21T08:33:12.332314-03:00",
      "tipo": "agotados",
      "especialidad": "PATOLOGIA MAMARIA (CON DERIVACION OBLIGATORIA)",
      "cupos": 0
    },
    {
      "fecha": "2026-05-21T15:27:28.582850-03:00",
      "tipo": "nuevos",
      "especialidad": "CIRUGIA GENERAL",
      "cupos": 21
    },
    {
      "fecha": "2026-05-21T15:27:28.582850-03:00",
      "tipo": "nuevos",
      "especialidad": "CIRUGIA INFANTIL",
      "cupos": 26
    },
    {
      "fecha": "2026-05-21T15:27:28.582850-03:00",
      "tipo": "nuevos",
      "especialidad": "CUIDADOS PALIATIVOS CON DERIVACION OBLIGATORIA",
      "cupos": 9
    },
    {
      "fecha": "2026-05-21T15:27:28.582850-03:00",
      "tipo": "nuevos",
      "especialidad": "DIABETOLOGIA GENERAL",
      "cupos": 1
    },
    {
      "fecha": "2026-05-21T15:27:28.582850-03:00",
      "tipo": "nuevos",
      "especialidad": "HEMATOLOGIA CLINICA",
      "cupos": 11
    },
    {
      "fecha": "2026-05-21T15:27:28.582850-03:00",
      "tipo": "nuevos",
      "especialidad": "INFECTOLOGIA",
      "cupos": 1
    },
    {
      "fecha": "2026-05-21T15:27:28.582850-03:00",
      "tipo": "nuevos",
      "especialidad": "NEFROLOGIA",
      "cupos": 1
    },
    {
      "fecha": "2026-05-21T15:27:28.582850-03:00",
      "tipo": "nuevos",
      "especialidad": "NEUMONOLOGIA INFANTIL",
      "cupos": 1
    },
    {
      "fecha": "2026-05-21T15:27:28.582850-03:00",
      "tipo": "nuevos",
      "especialidad": "NEUROLOGIA NUEVO (CON DERIVACIÓN)",
      "cupos": 1
    },
    {
      "fecha": "2026-05-21T15:27:28.582850-03:00",
      "tipo": "nuevos",
      "especialidad": "OBSTETRICIA BAJO RIESGO",
      "cupos": 38
    },
    {
      "fecha": "2026-05-21T15:27:28.582850-03:00",
      "tipo": "nuevos",
      "especialidad": "ONCOLOGIA",
      "cupos": 11
    },
    {
      "fecha": "2026-05-21T15:27:28.582850-03:00",
      "tipo": "nuevos",
      "especialidad": "PRE ANESTESIA PEDIATRIA",
      "cupos": 2
    },
    {
      "fecha": "2026-05-21T15:27:28.582850-03:00",
      "tipo": "nuevos",
      "especialidad": "REUMATOLOGIA (DERIVACION OBLIGATORIA)",
      "cupos": 1
    },
    {
      "fecha": "2026-05-21T15:27:28.582850-03:00",
      "tipo": "nuevos",
      "especialidad": "CIRUGIA TORACICA",
      "cupos": 7
    },
    {
      "fecha": "2026-05-21T15:27:28.582850-03:00",
      "tipo": "nuevos",
      "especialidad": "PODOLOGIA",
      "cupos": 2
    },
    {
      "fecha": "2026-05-21T19:51:17.118468-03:00",
      "tipo": "agotados",
      "especialidad": "NEUROLOGIA NUEVO (CON DERIVACIÓN)",
      "cupos": 0
    },
    {
      "fecha": "2026-05-22T06:41:13.105301-03:00",
      "tipo": "agotados",
      "especialidad": "NEUMONOLOGIA INFANTIL",
      "cupos": 0
    },
    {
      "fecha": "2026-05-22T06:41:13.105301-03:00",
      "tipo": "agotados",
      "especialidad": "PODOLOGIA",
      "cupos": 0
    },
    {
      "fecha": "2026-05-22T07:31:57.792894-03:00",
      "tipo": "nuevos",
      "especialidad": "CIRUGIA GENERAL",
      "cupos": 14
    },
    {
      "fecha": "2026-05-22T07:31:57.792894-03:00",
      "tipo": "nuevos",
      "especialidad": "CIRUGIA INFANTIL",
      "cupos": 24
    },
    {
      "fecha": "2026-05-22T07:31:57.792894-03:00",
      "tipo": "nuevos",
      "especialidad": "CUIDADOS PALIATIVOS CON DERIVACION OBLIGATORIA",
      "cupos": 9
    },
    {
      "fecha": "2026-05-22T07:31:57.792894-03:00",
      "tipo": "nuevos",
      "especialidad": "DIABETOLOGIA GENERAL",
      "cupos": 1
    },
    {
      "fecha": "2026-05-22T07:31:57.792894-03:00",
      "tipo": "nuevos",
      "especialidad": "HEMATOLOGIA CLINICA",
      "cupos": 6
    },
    {
      "fecha": "2026-05-22T07:31:57.792894-03:00",
      "tipo": "nuevos",
      "especialidad": "INFECTOLOGIA",
      "cupos": 1
    },
    {
      "fecha": "2026-05-22T07:31:57.792894-03:00",
      "tipo": "nuevos",
      "especialidad": "NEFROLOGIA",
      "cupos": 1
    },
    {
      "fecha": "2026-05-22T07:31:57.792894-03:00",
      "tipo": "nuevos",
      "especialidad": "OBSTETRICIA BAJO RIESGO",
      "cupos": 27
    },
    {
      "fecha": "2026-05-22T07:31:57.792894-03:00",
      "tipo": "nuevos",
      "especialidad": "ONCOLOGIA",
      "cupos": 8
    },
    {
      "fecha": "2026-05-22T07:31:57.792894-03:00",
      "tipo": "nuevos",
      "especialidad": "PRE ANESTESIA PEDIATRIA",
      "cupos": 1
    },
    {
      "fecha": "2026-05-22T07:31:57.792894-03:00",
      "tipo": "nuevos",
      "especialidad": "REUMATOLOGIA (DERIVACION OBLIGATORIA)",
      "cupos": 1
    },
    {
      "fecha": "2026-05-22T07:31:57.792894-03:00",
      "tipo": "nuevos",
      "especialidad": "CIRUGIA TORACICA",
      "cupos": 7
    },
    {
      "fecha": "2026-05-22T07:51:39.682088-03:00",
      "tipo": "nuevos",
      "especialidad": "CIRUGIA GENERAL",
      "cupos": 14
    },
    {
      "fecha": "2026-05-22T07:51:39.682088-03:00",
      "tipo": "nuevos",
      "especialidad": "CIRUGIA INFANTIL",
      "cupos": 24
    },
    {
      "fecha": "2026-05-22T07:51:39.682088-03:00",
      "tipo": "nuevos",
      "especialidad": "CUIDADOS PALIATIVOS CON DERIVACION OBLIGATORIA",
      "cupos": 9
    },
    {
      "fecha": "2026-05-22T07:51:39.682088-03:00",
      "tipo": "nuevos",
      "especialidad": "DIABETOLOGIA GENERAL",
      "cupos": 1
    },
    {
      "fecha": "2026-05-22T07:51:39.682088-03:00",
      "tipo": "nuevos",
      "especialidad": "HEMATOLOGIA CLINICA",
      "cupos": 6
    },
    {
      "fecha": "2026-05-22T07:51:39.682088-03:00",
      "tipo": "nuevos",
      "especialidad": "INFECTOLOGIA",
      "cupos": 1
    },
    {
      "fecha": "2026-05-22T07:51:39.682088-03:00",
      "tipo": "nuevos",
      "especialidad": "NEFROLOGIA",
      "cupos": 1
    },
    {
      "fecha": "2026-05-22T07:51:39.682088-03:00",
      "tipo": "nuevos",
      "especialidad": "OBSTETRICIA BAJO RIESGO",
      "cupos": 27
    },
    {
      "fecha": "2026-05-22T07:51:39.682088-03:00",
      "tipo": "nuevos",
      "especialidad": "ONCOLOGIA",
      "cupos": 8
    },
    {
      "fecha": "2026-05-22T07:51:39.682088-03:00",
      "tipo": "nuevos",
      "especialidad": "PRE ANESTESIA PEDIATRIA",
      "cupos": 1
    },
    {
      "fecha": "2026-05-22T07:51:39.682088-03:00",
      "tipo": "nuevos",
      "especialidad": "REUMATOLOGIA (DERIVACION OBLIGATORIA)",
      "cupos": 1
    },
    {
      "fecha": "2026-05-22T07:51:39.682088-03:00",
      "tipo": "nuevos",
      "especialidad": "CIRUGIA TORACICA",
      "cupos": 7
    },
    {
      "fecha": "2026-05-22T07:53:49.466156-03:00",
      "tipo": "nuevos",
      "especialidad": "CIRUGIA GENERAL",
      "cupos": 14
    },
    {
      "fecha": "2026-05-22T07:53:49.466156-03:00",
      "tipo": "nuevos",
      "especialidad": "CIRUGIA INFANTIL",
      "cupos": 24
    },
    {
      "fecha": "2026-05-22T07:53:49.466156-03:00",
      "tipo": "nuevos",
      "especialidad": "CUIDADOS PALIATIVOS CON DERIVACION OBLIGATORIA",
      "cupos": 9
    },
    {
      "fecha": "2026-05-22T07:53:49.466156-03:00",
      "tipo": "nuevos",
      "especialidad": "DIABETOLOGIA GENERAL",
      "cupos": 1
    },
    {
      "fecha": "2026-05-22T07:53:49.466156-03:00",
      "tipo": "nuevos",
      "especialidad": "HEMATOLOGIA CLINICA",
      "cupos": 6
    },
    {
      "fecha": "2026-05-22T07:53:49.466156-03:00",
      "tipo": "nuevos",
      "especialidad": "INFECTOLOGIA",
      "cupos": 1
    },
    {
      "fecha": "2026-05-22T07:53:49.466156-03:00",
      "tipo": "nuevos",
      "especialidad": "NEFROLOGIA",
      "cupos": 1
    },
    {
      "fecha": "2026-05-22T07:53:49.466156-03:00",
      "tipo": "nuevos",
      "especialidad": "OBSTETRICIA BAJO RIESGO",
      "cupos": 27
    },
    {
      "fecha": "2026-05-22T07:53:49.466156-03:00",
      "tipo": "nuevos",
      "especialidad": "ONCOLOGIA",
      "cupos": 8
    },
    {
      "fecha": "2026-05-22T07:53:49.466156-03:00",
      "tipo": "nuevos",
      "especialidad": "PRE ANESTESIA PEDIATRIA",
      "cupos": 1
    },
    {
      "fecha": "2026-05-22T07:53:49.466156-03:00",
      "tipo": "nuevos",
      "especialidad": "REUMATOLOGIA (DERIVACION OBLIGATORIA)",
      "cupos": 1
    },
    {
      "fecha": "2026-05-22T07:53:49.466156-03:00",
      "tipo": "nuevos",
      "especialidad": "CIRUGIA TORACICA",
      "cupos": 7
    },
    {
      "fecha": "2026-05-22T07:58:44.873510-03:00",
      "tipo": "nuevos",
      "especialidad": "CIRUGIA GENERAL",
      "cupos": 14
    },
    {
      "fecha": "2026-05-22T07:58:44.873510-03:00",
      "tipo": "nuevos",
      "especialidad": "CIRUGIA INFANTIL",
      "cupos": 24
    },
    {
      "fecha": "2026-05-22T07:58:44.873510-03:00",
      "tipo": "nuevos",
      "especialidad": "CUIDADOS PALIATIVOS CON DERIVACION OBLIGATORIA",
      "cupos": 9
    },
    {
      "fecha": "2026-05-22T07:58:44.873510-03:00",
      "tipo": "nuevos",
      "especialidad": "DIABETOLOGIA GENERAL",
      "cupos": 1
    },
    {
      "fecha": "2026-05-22T07:58:44.873510-03:00",
      "tipo": "nuevos",
      "especialidad": "HEMATOLOGIA CLINICA",
      "cupos": 6
    },
    {
      "fecha": "2026-05-22T07:58:44.873510-03:00",
      "tipo": "nuevos",
      "especialidad": "INFECTOLOGIA",
      "cupos": 1
    },
    {
      "fecha": "2026-05-22T07:58:44.873510-03:00",
      "tipo": "nuevos",
      "especialidad": "NEFROLOGIA",
      "cupos": 1
    },
    {
      "fecha": "2026-05-22T07:58:44.873510-03:00",
      "tipo": "nuevos",
      "especialidad": "OBSTETRICIA BAJO RIESGO",
      "cupos": 27
    },
    {
      "fecha": "2026-05-22T07:58:44.873510-03:00",
      "tipo": "nuevos",
      "especialidad": "ONCOLOGIA",
      "cupos": 8
    },
    {
      "fecha": "2026-05-22T07:58:44.873510-03:00",
      "tipo": "nuevos",
      "especialidad": "PRE ANESTESIA PEDIATRIA",
      "cupos": 1
    },
    {
      "fecha": "2026-05-22T07:58:44.873510-03:00",
      "tipo": "nuevos",
      "especialidad": "REUMATOLOGIA (DERIVACION OBLIGATORIA)",
      "cupos": 1
    },
    {
      "fecha": "2026-05-22T07:58:44.873510-03:00",
      "tipo": "nuevos",
      "especialidad": "CIRUGIA TORACICA",
      "cupos": 7
    },
    {
      "fecha": "2026-05-22T08:51:27.334842-03:00",
      "tipo": "ultimos",
      "especialidad": "HEMATOLOGIA CLINICA",
      "cupos": 4
    },
    {
      "fecha": "2026-05-22T08:51:27.334842-03:00",
      "tipo": "agotados",
      "especialidad": "REUMATOLOGIA (DERIVACION OBLIGATORIA)",
      "cupos": 0
    }
  ]
}