{
  "PEDIATRIA CONSULTA": 0,
  "ODONTOLOGIA ADULTO": 0,
  "CIRUGIA GENERAL": 96,
  "CIRUGIA INFANTIL": 55,
  "CLINICA MEDICA CONSULTA": 0,
  "CUIDADOS PALIATIVOS CON DERIVACION OBLIGATORIA": 7,
  "DERMATOLOGIA GENERAL": 0,
  "DIABETOLOGIA GENERAL": 41,
  "FLEBOLOGIA (CONSULTA)": 0,
  "FONOAUDIOLOGIA AUDIOMETRIA (SOLO CON DERIVACIÓN)": 0,
  "HEMATOLOGIA CLINICA": 47,
  "INFECTOLOGIA": 6,
  "INFECTOLOGIA PEDIATRICA": 16,
  "PATOLOGIA MAMARIA (CON DERIVACION OBLIGATORIA)": 7,
  "NEFROLOGIA": 3,
  "NEUMONOLOGIA ADULTO (CON DERIVACIÓN)": 0,
  "NEUMONOLOGIA INFANTIL": 4,
  "NEUROLOGIA NUEVO (CON DERIVACIÓN)": 0,
  "NUTRICION GENERAL": 0,
  "OBSTETRICIA BAJO RIESGO": 173,
  "OFTALMOLOGIA": 0,
  "ONCOLOGIA": 39,
  "ORL CONSULTAS": 0,
  "PRE ANESTESIA PEDIATRIA": 16,
  "REUMATOLOGIA (DERIVACION OBLIGATORIA)": 0,
  "TRAUMATOLOGIA ADULTO": 0,
  "TRAUMATOLOGIA INFANTIL": 0,
  "UROLOGIA": 1,
  "VASCULAR PERIFERICO (OBLIGATORIO DERIVACION PACIENTE NUEVO)": 8,
  "CARDIOLOGIA ADULTO": 0,
  "CARDIOLOGIA INFANTIL": 0,
  "COLOPROCTOLOGIA": 11,
  "CIRUGIA TORACICA": 10,
  "PEDIATRIA MEDIANO RIESGO": 0,
  "ODONTOLOGÍA PEDIATRICA": 0,
  "PODOLOGIA": 54,
  "ESPIROMETRIA ADULTO (CON DERIVACIÓN)": 9,
  "ESPIROMETRIA NIÑOS (CON DERIVACIÓN)": 1,
  "ECOCARDIOGRAMA DOPPLER ADULTO (DERIVACION OBLIGATORIA)": 0,
  "ELECTROCARDIOGRAMA ADULTO(CON DERIVACION)": 0
}